{
    "name": "Python Poetry Development with Rclone",
    "dockerFile": "Dockerfile",
    "forwardPorts": [8000],
    "customizations": {
        "vscode": {
            "extensions": [
                "ms-python.python",
                "ms-python.vscode-pylance",
                "ms-python.black-formatter",
                "ms-azuretools.vscode-docker"
            ],
            "settings": {
                "python.defaultInterpreterPath": "/usr/local/bin/python",
                "python.linting.enabled": true,
                "python.formatting.provider": "black",
                "editor.formatOnSave": true,
                "editor.rulers": [88]
            }
        }
    },
    "runArgs": [
        "--cap-add=SYS_ADMIN",
        "--device=/dev/fuse",
        "--security-opt=apparmor:unconfined",
        "--privileged"
    ],
    "remoteUser": "vscode",
    "workspaceFolder": "/workspace",
    "onCreateCommand": "sudo bash /workspace/.devcontainer/setup.sh",
    "postStartCommand": "sudo bash /workspace/.devcontainer/start.sh",
    "waitFor": "onCreateCommand"
}